decfunc/__init__.py
decfunc-1.0.0.dist-info/LICENSE
decfunc-1.0.0.dist-info/METADATA
decfunc-1.0.0.dist-info/WHEEL
decfunc-1.0.0.dist-info/top_level.txt
decfunc-1.0.0.dist-info/RECORD
