Metadata-Version: 2.1
Name: decfunc
Version: 1.0.0
Summary: Creating decorators with arguments made easy.
Home-page: https://github.com/realsuayip/decfunc
Author: Şuayip Üzülmez
Author-email: suayip.541@gmail.com
License: UNKNOWN
Platform: UNKNOWN
Classifier: Programming Language :: Python :: 3
Classifier: License :: OSI Approved :: MIT License
Classifier: Operating System :: OS Independent
Requires-Python: >=3.7
License-File: LICENSE
